betterfunctions/__init__.py
betterfunctions/filefunctions.py
betterfunctions/mathfunctions.py
betterfunctions/randomfunctions.py
betterfunctions/textfunctions.py
betterfunctions/timefunctions.py
betterfunctions/userinputfunctions.py
betterfunctions-0.1.1.dist-info/LICENSE
betterfunctions-0.1.1.dist-info/METADATA
betterfunctions-0.1.1.dist-info/WHEEL
betterfunctions-0.1.1.dist-info/top_level.txt
betterfunctions-0.1.1.dist-info/RECORD
