Metadata-Version: 2.1
Name: betterfunctions
Version: 0.1.1
Summary: A lib with python function improvements
Author-email: konnija <contact@konja-rehm.de>
License: MIT
Project-URL: GitHub, https://github.com/nokohokon/BetterFunctions
Keywords: functions,improvements,python-functions
Classifier: Development Status :: 4 - Beta
Classifier: License :: OSI Approved :: MIT License
Classifier: Intended Audience :: Developers
Classifier: Operating System :: OS Independent
Classifier: Programming Language :: Python :: 3.9
Classifier: Programming Language :: Python :: 3.10
Classifier: Programming Language :: Python :: 3.11
Classifier: Programming Language :: Python :: 3.12
Requires-Python: >=3.9
License-File: LICENSE
Requires-Dist: sphinx
Requires-Dist: furo
Requires-Dist: sphinx-autodoc-typehints
Requires-Dist: sphinx-copybutton
Requires-Dist: myst-parser
Requires-Dist: pytz
